README.md
setup.cfg
setup.py
bin/remotedev
bin/remotedev.py
pyremotedev/__init__.py
pyremotedev/config.py
pyremotedev/consts.py
pyremotedev/file.py
pyremotedev/logs.py
pyremotedev/pyremotedev.py
pyremotedev/request.py
pyremotedev/synchronizer.py
pyremotedev/version.py
remotedev.egg-info/PKG-INFO
remotedev.egg-info/SOURCES.txt
remotedev.egg-info/dependency_links.txt
remotedev.egg-info/requires.txt
remotedev.egg-info/top_level.txt