Metadata-Version: 1.2
Name: remotedev
Version: 0.0.15
Summary: Sync your development env to your application execution env
Home-page: http://www.github.com/tangb/remotedev/
Author: Tanguy Bonneau
Author-email: tanguy.bonneau@gmail.com
Maintainer: Tanguy Bonneau
Maintainer-email: tanguy.bonneau@gmail.com
License: UNKNOWN
Platform: UNKNOWN
